pyrealty/__init__.py
pyrealty/core/__init__.py
pyrealty/core/filters.py
pyrealty/core/helpers.py
pyrealty/core/models.py
pyrealty/core/storage.py
pyrealty/src/__init__.py
pyrealty/src/_api_request.py
pyrealty/src/_base_request.py
pyrealty/src/_errors.py
pyrealty/src/constants.py
pyrealty/src/logger.py
pyrealty/src/utils.py
property_blob-0.1.1.dist-info/METADATA
property_blob-0.1.1.dist-info/WHEEL
property_blob-0.1.1.dist-info/RECORD
