Metadata-Version: 2.3
Name: property-blob
Version: 0.1.1
Summary: Demo description here.
License: MIT
Keywords: pyrealty,DataDockAI,python,Real Estate
Author: DataDock-AI
Author-email: api@datadock.ai
Maintainer: Peter Mbachu
Maintainer-email: peter.mbachu@datadock.ai
Requires-Python: >=3.10,<4.0
Classifier: Development Status :: 5 - Production/Stable
Classifier: Intended Audience :: Developers
Classifier: License :: OSI Approved :: MIT License
Classifier: Natural Language :: English
Classifier: Operating System :: OS Independent
Classifier: Programming Language :: Python :: 3
Classifier: Programming Language :: Python :: 3.10
Classifier: Programming Language :: Python :: 3.11
Classifier: Programming Language :: Python :: 3.12
Classifier: Programming Language :: Python :: 3.13
Classifier: Topic :: Software Development :: Libraries :: Python Modules
Requires-Dist: aiohttp (>=3.11.12,<4.0.0)
Requires-Dist: beautifulsoup4 (>=4.12.3,<5.0.0)
Requires-Dist: colorama (>=0.4.6,<0.5.0)
Requires-Dist: fastcore (>=1.7.17,<2.0.0)
Requires-Dist: humanize (>=4.11.0,<5.0.0)
Requires-Dist: ipykernel (>=6.29.5,<7.0.0)
Requires-Dist: lxml (>=5.3.0,<6.0.0)
Requires-Dist: pandas (>=2.2.3,<3.0.0)
Requires-Dist: pyarrow (>=17.0.0,<18.0.0)
Requires-Dist: pydantic (>=2.9.2,<3.0.0)
Requires-Dist: python-decouple (>=3.8,<4.0)
Requires-Dist: rich (>=13.8.1,<14.0.0)
Requires-Dist: tabulate (>=0.9.0,<0.10.0)
